[
   {
      "label":"January",
      "values":{
         "Q1":140.0754,
         "Q2":201.7292,
         "Q3":226.02957500000002,
         "wisker_low":113.9177,
         "whisker_low":306.4633
      }
   },
   {
      "label":"February",
      "values":{
         "Q1":144.4092,
         "Q2":208.02355,
         "Q3":233.7169,
         "wisker_low":118.4579,
         "whisker_low":277.7775
      }
   },
   {
      "label":"March",
      "values":{
         "Q1":135.947925,
         "Q2":187.69585,
         "Q3":209.6745,
         "wisker_low":109.9966,
         "whisker_low":254.251
      }
   },
   {
      "label":"April",
      "values":{
         "Q1":134.86450000000002,
         "Q2":178.0995,
         "Q3":202.8642,
         "wisker_low":111.0284,
         "whisker_low":251.1554
      }
   },
   {
      "label":"May",
      "values":{
         "Q1":123.2044,
         "Q2":156.8431,
         "Q3":182.227,
         "wisker_low":88.94657,
         "whisker_low":260.0294
      }
   },
   {
      "label":"June",
      "values":{
         "Q1":111.4412,
         "Q2":143.22255,
         "Q3":168.6064,
         "wisker_low":75.73873,
         "whisker_low":261.6804
      }
   },
   {
      "label":"July",
      "values":{
         "Q1":106.0239,
         "Q2":139.9206,
         "Q3":161.7961,
         "wisker_low":65.4201,
         "whisker_low":250.5363
      }
   },
   {
      "label":"August",
      "values":{
         "Q1":108.08760000000001,
         "Q2":155.5017,
         "Q3":183.10407500000002,
         "wisker_low":81.72353,
         "whisker_low":257.1402
      }
   },
   {
      "label":"September",
      "values":{
         "Q1":113.86609999999999,
         "Q2":170.1542,
         "Q3":197.55010000000002,
         "wisker_low":85.43824,
         "whisker_low":254.6637
      }
   },
   {
      "label":"October",
      "values":{
         "Q1":123.15280000000001,
         "Q2":185.8385,
         "Q3":206.9917,
         "wisker_low":94.10589,
         "whisker_low":258.1721
      }
   },
   {
      "label":"November",
      "values":{
         "Q1":133.0587,
         "Q2":188.6245,
         "Q3":214.3179,
         "wisker_low":106.901,
         "whisker_low":266.6333
      }
   },
   {
      "label":"December",
      "values":{
         "Q1":145.4927,
         "Q2":206.6821,
         "Q3":231.55,
         "wisker_low":119.6961,
         "whisker_low":287.2706
      }
   }
]